<?xml version="1.0" encoding="windows-1252"?>
<faces-config version="1.2" xmlns="http://java.sun.com/xml/ns/javaee">
 <managed-bean>
    <managed-bean-name>detalleOrganizacion</managed-bean-name>
    <managed-bean-class>co.gov.ideam.sirh.directorio.view.DetalleOrganizacionBean</managed-bean-class>
    <managed-bean-scope>session</managed-bean-scope>
    <!--oracle-jdev-comment:managed-bean-jsp-link:1directorio/detalleOrganizacion.jspx-->
  </managed-bean>
  <managed-bean>
    <managed-bean-name>especialistas</managed-bean-name>
    <managed-bean-class>co.gov.ideam.sirh.directorio.view.ListaEspecialistasBean</managed-bean-class>
    <managed-bean-scope>session</managed-bean-scope>
    <!--oracle-jdev-comment:managed-bean-jsp-link:1directorio/listaEspecialistas.jspx-->
  </managed-bean>
  <managed-bean>
    <managed-bean-name>detalleEspecialista</managed-bean-name>
    <managed-bean-class>co.gov.ideam.sirh.directorio.view.DetalleEspecialistaBean</managed-bean-class>
    <managed-bean-scope>session</managed-bean-scope>
    <!--oracle-jdev-comment:managed-bean-jsp-link:1directorio/detalleEspecialista.jspx-->
  </managed-bean>
  <managed-bean>
    <managed-bean-name>consultaDirectorio</managed-bean-name>
    <managed-bean-class>co.gov.ideam.sirh.directorio.view.ConsultaBean</managed-bean-class>
    <managed-bean-scope>session</managed-bean-scope>
    <!--oracle-jdev-comment:managed-bean-jsp-link:1directorio/consulta.jspx-->
  </managed-bean>
  <managed-bean>
    <managed-bean-name>resultadoConsulta</managed-bean-name>
    <managed-bean-class>co.gov.ideam.sirh.directorio.view.ResultadoConsultaBean</managed-bean-class>
    <managed-bean-scope>session</managed-bean-scope>
    <!--oracle-jdev-comment:managed-bean-jsp-link:1directorio/resultadoConsulta.jspx-->
  </managed-bean>
  <managed-bean>
    <managed-bean-name>consultaOrganizaciones</managed-bean-name>
    <managed-bean-class>co.gov.ideam.sirh.directorio.view.ConsultaOrganizacionesBean</managed-bean-class>
    <managed-bean-scope>session</managed-bean-scope>
    <!--oracle-jdev-comment:managed-bean-jsp-link:1directorio/consultaOrganizaciones.jspx-->
  </managed-bean>
  <managed-bean>
    <managed-bean-name>resultadoConsultaOrganizaciones</managed-bean-name>
    <managed-bean-class>co.gov.ideam.sirh.directorio.view.ResultadoConsultaOrganizacionesBean</managed-bean-class>
    <managed-bean-scope>session</managed-bean-scope>
    <!--oracle-jdev-comment:managed-bean-jsp-link:1directorio/resultadoConsultaOrganizaciones.jspx-->
  </managed-bean> 
  <managed-bean>
    <managed-bean-name>formacionEspecialistas</managed-bean-name>
    <managed-bean-class>co.gov.ideam.sirh.estadisticas.view.FormacionEspecialistasBean</managed-bean-class>
    <managed-bean-scope>session</managed-bean-scope>
    <!--oracle-jdev-comment:managed-bean-jsp-link:1directorio/formacionEspecialistas.jsff-->
  </managed-bean> 
   <managed-bean>
    <managed-bean-name>investigacionGestion</managed-bean-name>
    <managed-bean-class>co.gov.ideam.sirh.estadisticas.view.InvestigacionGestionBean</managed-bean-class>
    <managed-bean-scope>session</managed-bean-scope>
    <!--oracle-jdev-comment:managed-bean-jsp-link:1directorio/investigacionGestion.jsff-->
  </managed-bean> 
     <managed-bean>
    <managed-bean-name>gestionEspecialistas</managed-bean-name>
    <managed-bean-class>co.gov.ideam.sirh.estadisticas.view.GestionEspecialistasBean</managed-bean-class>
    <managed-bean-scope>session</managed-bean-scope>
    <!--oracle-jdev-comment:managed-bean-jsp-link:1directorio/gestionEspecialistas.jsff-->
  </managed-bean> 
  
  
  <navigation-rule>
    <from-view-id>/directorio/listaOrganizaciones.jspx</from-view-id>
    <navigation-case>
      <from-outcome>detalleOrganizacion</from-outcome>
      <to-view-id>/directorio/detalleOrganizacion.jspx</to-view-id>
      <redirect/>
    </navigation-case>
  </navigation-rule>
  <navigation-rule>
    <navigation-case>
      <from-outcome>organizaciones</from-outcome>
      <to-view-id>/directorio/listaOrganizaciones.jspx</to-view-id>
      <redirect/>
    </navigation-case>
    <navigation-case>
      <from-outcome>especialistas</from-outcome>
      <to-view-id>/directorio/listaEspecialistas.jspx</to-view-id>
      <redirect/>
    </navigation-case>
    <navigation-case>
      <from-outcome>consulta</from-outcome>
      <to-view-id>/directorio/consulta.jspx</to-view-id>
      <redirect/>
    </navigation-case>
    <navigation-case>
      <from-outcome>consultaEspecialistas</from-outcome>
      <to-view-id>/directorio/resultadoConsulta.jspx</to-view-id>
      <redirect/>
    </navigation-case>
    <navigation-case>
      <from-outcome>consultaOrganizaciones</from-outcome>
      <to-view-id>/directorio/consultaOrganizaciones.jspx</to-view-id>
      <redirect/>
    </navigation-case>
    <navigation-case>
      <from-outcome>resultadoConsultaOrganizaciones</from-outcome>
      <to-view-id>/directorio/resultadoConsultaOrganizaciones.jspx</to-view-id>
      <redirect/>
    </navigation-case>
  </navigation-rule>
  <managed-bean>
    <managed-bean-name>organizaciones</managed-bean-name>
    <managed-bean-class>co.gov.ideam.sirh.directorio.view.ListaOrganizacionesBean</managed-bean-class>
    <managed-bean-scope>session</managed-bean-scope>
    <!--oracle-jdev-comment:managed-bean-jsp-link:1directorio/listaOrganizaciones.jspx-->
  </managed-bean>
  <navigation-rule>
    <from-view-id>/directorio/listaEspecialistas.jspx</from-view-id>
    <navigation-case>
      <from-outcome>detalleEspecialista</from-outcome>
      <to-view-id>/directorio/detalleEspecialista.jspx</to-view-id>
      <redirect/>
    </navigation-case>
  </navigation-rule>
  <managed-bean>
    <managed-bean-name>detalleEspecialistaExterno</managed-bean-name>
    <managed-bean-class>co.gov.ideam.sirh.directorio.view.DetalleEspecialistaExternoBean</managed-bean-class>
    <managed-bean-scope>session</managed-bean-scope>
  </managed-bean>
  <navigation-rule>
    <from-view-id>/directorio/resultadoConsulta.jspx</from-view-id>
    <navigation-case>
      <from-outcome>detalleEspecialistaExterno</from-outcome>
      <to-view-id>/directorio/detalleEspecialistaExterno.jspx</to-view-id>
    </navigation-case>
  </navigation-rule>
  <navigation-rule>
    <from-view-id>/directorio/detalleEspecialistaExterno.jspx</from-view-id>
    <navigation-case>
     <from-outcome>consulta</from-outcome>
      <to-view-id>/directorio/consulta.jspx</to-view-id>
     
    </navigation-case>
  </navigation-rule>
</faces-config>