<?xml version="1.0" encoding="windows-1252"?>
<faces-config version="1.2" xmlns="http://java.sun.com/xml/ns/javaee">
  <managed-bean>
    <managed-bean-name>priorizacion</managed-bean-name>
    <managed-bean-class>co.gov.ideam.sirh.porh.view.PriorizacionBean</managed-bean-class>
    <managed-bean-scope>session</managed-bean-scope>
  </managed-bean>
  <managed-bean>
    <managed-bean-name>metas</managed-bean-name>
    <managed-bean-class>co.gov.ideam.sirh.porh.view.MetasBean</managed-bean-class>
    <managed-bean-scope>session</managed-bean-scope>
    <!--oracle-jdev-comment:managed-bean-jsp-link:1porh/metas.jspx-->
  </managed-bean>
  <navigation-rule>
    <from-view-id>/fuentes/fuentes.jspx</from-view-id>
    <navigation-case>
      <from-outcome>establecerPorh</from-outcome>
      <to-view-id>/porh/priorizacion.jspx</to-view-id>
      <redirect/>
    </navigation-case>
  </navigation-rule>
  <navigation-rule>
    <from-view-id>/porh/ofertaDemanda.jspx</from-view-id>
    <navigation-case>
      <from-outcome>puntosMonitoreoTramo</from-outcome>
      <to-view-id>/porh/puntosMonitoreo.jspx</to-view-id>
      <redirect/>
    </navigation-case>
    <navigation-case>
      <from-outcome>detalleFuente</from-outcome>
      <to-view-id>/fuentes/detalleFuente.jspx</to-view-id>
      <redirect/>
    </navigation-case>
    <navigation-case>
      <from-outcome>detalleTramo</from-outcome>
      <to-view-id>/fuentes/detalleTramo.jspx</to-view-id>
      <redirect/>
    </navigation-case>
    <navigation-case>
      <from-outcome>priorizacion</from-outcome>
      <to-view-id>/porh/priorizacion.jspx</to-view-id>
      <redirect/>
    </navigation-case>
  </navigation-rule>
  <managed-bean>
    <managed-bean-name>usosPermitidos</managed-bean-name>
    <managed-bean-class>co.gov.ideam.sirh.porh.view.UsosPermitidosBean</managed-bean-class>
    <managed-bean-scope>session</managed-bean-scope>
  </managed-bean>
  <navigation-rule>
    <from-view-id>/porh/usosPermitidos.jspx</from-view-id>
    <navigation-case>
      <from-outcome>detalleFuente</from-outcome>
      <to-view-id>/fuentes/detalleFuente.jspx</to-view-id>
      <redirect/>
    </navigation-case>
    <navigation-case>
      <from-outcome>detalleTramo</from-outcome>
      <to-view-id>/fuentes/detalleTramo.jspx</to-view-id>
      <redirect/>
    </navigation-case>
    <navigation-case>
      <from-outcome>priorizacion</from-outcome>
      <to-view-id>/porh/priorizacion.jspx</to-view-id>
      <redirect/>
    </navigation-case>
  </navigation-rule>
  <navigation-rule>
    <from-view-id>/porh/priorizacion.jspx</from-view-id>
    <navigation-case>
      <from-outcome>puntosMonitoreoTramo</from-outcome>
      <to-view-id>/porh/puntosMonitoreo.jspx</to-view-id>
      <redirect/>
    </navigation-case>
    <navigation-case>
      <from-outcome>ofertaDemanda</from-outcome>
      <to-view-id>/porh/ofertaDemanda.jspx</to-view-id>
      <redirect/>
    </navigation-case>
    <navigation-case>
      <from-outcome>usosPermitidos</from-outcome>
      <to-view-id>/porh/usosPermitidos.jspx</to-view-id>
      <redirect/>
    </navigation-case>
    <navigation-case>
      <from-outcome>prohibiciones</from-outcome>
      <to-view-id>/porh/razonesProhibicion.jspx</to-view-id>
      <redirect/>
    </navigation-case>
    <navigation-case>
      <from-outcome>metasDescontaminacion</from-outcome>
      <to-view-id>/porh/metas.jspx</to-view-id>
      <redirect/>
    </navigation-case>
    <navigation-case>
      <from-outcome>indicadores</from-outcome>
      <to-view-id>/porh/indices.jspx</to-view-id>
      <redirect/>
    </navigation-case>
    <navigation-case>
    <from-outcome>adicionarConflictoTramo</from-outcome>
      <to-view-id>/fuentes/conflicto.jspx</to-view-id>
    </navigation-case>
    <navigation-case>
    <from-outcome>afluentesTramo</from-outcome>
      <to-view-id>/porh/tramoAfluentes.jspx</to-view-id>
    </navigation-case>
    <navigation-case>
    <from-outcome>riesgosTramo</from-outcome>
      <to-view-id>/porh/riesgosTramo.jspx</to-view-id>
    </navigation-case>
  </navigation-rule>
  
  <navigation-rule>
    <from-view-id>/porh/tramoAfluentes.jspx</from-view-id>
   <navigation-case>
      <from-outcome>detalleFuente</from-outcome>
      <to-view-id>/fuentes/detalleFuente.jspx</to-view-id>
      <redirect/>
    </navigation-case>
    <navigation-case>
      <from-outcome>priorizacion</from-outcome>
      <to-view-id>/porh/priorizacion.jspx</to-view-id>
      <redirect/>
    </navigation-case>
  </navigation-rule>
  
  <navigation-rule>
    <from-view-id>/porh/riesgosTramo.jspx</from-view-id>
   <navigation-case>
      <from-outcome>detalleFuente</from-outcome>
      <to-view-id>/fuentes/detalleFuente.jspx</to-view-id>
      <redirect/>
    </navigation-case>
    <navigation-case>
      <from-outcome>priorizacion</from-outcome>
      <to-view-id>/porh/priorizacion.jspx</to-view-id>
      <redirect/>
    </navigation-case>
  </navigation-rule>
  
  <managed-bean>
    <managed-bean-name>puntosMonitoreo</managed-bean-name>
    <managed-bean-class>co.gov.ideam.sirh.porh.view.PuntosMonitoreoBean</managed-bean-class>
    <managed-bean-scope>session</managed-bean-scope>
  </managed-bean>
  <managed-bean>
    <managed-bean-name>tramoAfluentes</managed-bean-name>
    <managed-bean-class>co.gov.ideam.sirh.porh.view.TramoAfluentes</managed-bean-class>
    <managed-bean-scope>session</managed-bean-scope>
  </managed-bean>
  <managed-bean>
    <managed-bean-name>riesgosTramo</managed-bean-name>
    <managed-bean-class>co.gov.ideam.sirh.porh.view.RiesgosTramo</managed-bean-class>
    <managed-bean-scope>session</managed-bean-scope>
  </managed-bean>
  <navigation-rule>
    <from-view-id>/porh/puntosMonitoreo.jspx</from-view-id>
    <navigation-case>
      <from-outcome>priorizacion</from-outcome>
      <to-view-id>/porh/priorizacion.jspx</to-view-id>
      <redirect/>
    </navigation-case>
    <navigation-case>
      <from-outcome>ofertaDemanda</from-outcome>
      <to-view-id>/porh/ofertaDemanda.jspx</to-view-id>
      <redirect/>
    </navigation-case>
    <navigation-case>
      <from-outcome>usosPermitidos</from-outcome>
      <to-view-id>/porh/usosPermitidos.jspx</to-view-id>
      <redirect/>
    </navigation-case>
    <navigation-case>
      <from-outcome>prohibiciones</from-outcome>
      <to-view-id>/porh/razonesProhibicion.jspx</to-view-id>
      <redirect/>
    </navigation-case>
    <navigation-case>
      <from-outcome>metasDescontaminacion</from-outcome>
      <to-view-id>/porh/metas.jspx</to-view-id>
      <redirect/>
    </navigation-case>
    <navigation-case>
      <from-outcome>indicadores</from-outcome>
      <to-view-id>/porh/indices.jspx</to-view-id>
      <redirect/>
    </navigation-case>
  </navigation-rule>
  <managed-bean>
    <managed-bean-name>razonesProhibicion</managed-bean-name>
    <managed-bean-class>co.gov.ideam.sirh.porh.view.RazonesProhibicionBean</managed-bean-class>
    <managed-bean-scope>session</managed-bean-scope>
  </managed-bean>
  <managed-bean>
    <managed-bean-name>metasDescontaminacion</managed-bean-name>
    <managed-bean-class>co.gov.ideam.sirh.porh.view.MetasDescontaminacionBean</managed-bean-class>
    <managed-bean-scope>session</managed-bean-scope>
  </managed-bean>
  <navigation-rule>
    <from-view-id>/porh/metasDescontaminacion.jspx</from-view-id>
    <navigation-case>
      <from-outcome>detalleFuente</from-outcome>
      <to-view-id>/fuentes/detalleFuente.jspx</to-view-id>
      <redirect/>
    </navigation-case>
    <navigation-case>
      <from-outcome>detalleTramo</from-outcome>
      <to-view-id>/fuentes/detalleTramo.jspx</to-view-id>
      <redirect/>
    </navigation-case>
    <navigation-case>
      <from-outcome>priorizacion</from-outcome>
      <to-view-id>/porh/priorizacion.jspx</to-view-id>
      <redirect/>
    </navigation-case>
  </navigation-rule>
  <managed-bean>
    <managed-bean-name>graficoEfectividad</managed-bean-name>
    <managed-bean-class>co.gov.ideam.sirh.porh.view.GraficoEfectividadBean</managed-bean-class>
    <managed-bean-scope>request</managed-bean-scope>
    <!--oracle-jdev-comment:managed-bean-jsp-link:1porh/graficoEfectividad.jsff-->
  </managed-bean>  
  <managed-bean>
    <managed-bean-name>indices</managed-bean-name>
    <managed-bean-class>co.gov.ideam.sirh.porh.view.IndicesBean</managed-bean-class>
    <managed-bean-scope>session</managed-bean-scope>
    <!--oracle-jdev-comment:managed-bean-jsp-link:1porh/indices.jspx-->
  </managed-bean>
  <navigation-rule>
    <from-view-id>/porh/razonesProhibicion.jspx</from-view-id>
    <navigation-case>
      <from-outcome>priorizacion</from-outcome>
      <to-view-id>/porh/priorizacion.jspx</to-view-id>
      <redirect/>
    </navigation-case>
  </navigation-rule>
  <navigation-rule>
    <from-view-id>/porh/indices.jspx</from-view-id>
    <navigation-case>
      <from-outcome>priorizacion</from-outcome>
      <to-view-id>/porh/priorizacion.jspx</to-view-id>
      <redirect/>
    </navigation-case>
	<navigation-case>
      <from-outcome>puntosMonitoreoTramo</from-outcome>
      <to-view-id>/porh/puntosMonitoreo.jspx</to-view-id>
      <redirect/>
    </navigation-case>

  </navigation-rule>
  <navigation-rule>
    <from-view-id>/porh/metas.jspx</from-view-id>
    <navigation-case>
      <from-outcome>priorizacion</from-outcome>
      <to-view-id>/porh/priorizacion.jspx</to-view-id>
      <redirect/>
    </navigation-case>
    <navigation-case>
      <from-outcome>detalleFuente</from-outcome>
      <to-view-id>/fuentes/detalleFuente.jspx</to-view-id>
      <redirect/>
    </navigation-case>
    <navigation-case>
      <from-outcome>detalleTramo</from-outcome>
      <to-view-id>/fuentes/detalleTramo.jspx</to-view-id>
      <redirect/>
    </navigation-case>
    </navigation-rule>
   
      <navigation-rule>
    <from-view-id>/porh/ofertaDemanda.jspx</from-view-id>
    <navigation-case>
      <from-outcome>priorizacion</from-outcome>
      <to-view-id>/porh/priorizacion.jspx</to-view-id>
      <redirect/>
    </navigation-case>
     <navigation-case>
      <from-outcome>fuentes</from-outcome>
      <to-view-id>/fuentes/fuentes.jspx</to-view-id>
      <redirect/>
    </navigation-case>
    <navigation-case>
      <from-outcome>detalleFuente</from-outcome>
      <to-view-id>/fuentes/detalleFuente.jspx</to-view-id>
      <redirect/>
    </navigation-case>
     <navigation-case>
     <from-outcome>detalleTramo</from-outcome>
      <to-view-id>/fuentes/detalleTramo.jspx</to-view-id>
      <redirect/>
    </navigation-case>
  </navigation-rule>
  
</faces-config>